README.rst
setup.py
test_song.egg-info/PKG-INFO
test_song.egg-info/SOURCES.txt
test_song.egg-info/dependency_links.txt
test_song.egg-info/top_level.txt
utils/__init__.py
utils/combdata.py