Metadata-Version: 1.1
Name: test-song
Version: 0.0.2
Summary: test utils
Home-page: https://github.com/songjian28/util_test
Author: SONG JIAN
Author-email: songjian9228@163.com
License: MIT
Keywords: util jian
Platform: UNKNOWN
Classifier: Development Status :: 3 - Alpha
Classifier: Intended Audience :: Developers
Classifier: Topic :: Software Development :: Build Tools
Classifier: License :: OSI Approved :: MIT License
Classifier: Programming Language :: Python
Classifier: Programming Language :: Python :: 2
Classifier: Programming Language :: Python :: 2.6
Classifier: Programming Language :: Python :: 2.7
